jupyter_tincan/__init__.py
jupyter_tincan/__main__.py
jupyter_tincan/cli.py
jupyter_tincan/html.py
jupyter_tincan/proxy.py
jupyter_tincan/text2svg.js
jupyter_tincan/text2svg.py
jupyter_tincan-0.1.1.dist-info/LICENSE
jupyter_tincan-0.1.1.dist-info/METADATA
jupyter_tincan-0.1.1.dist-info/WHEEL
jupyter_tincan-0.1.1.dist-info/entry_points.txt
jupyter_tincan-0.1.1.dist-info/RECORD
