Metadata-Version: 2.1
Name: jupyter-tincan
Version: 0.1.1
Summary: 
License: MIT
Author: Roberto Abdelkader Martínez Pérez
Author-email: robertomartinezp@gmail.com
Requires-Python: >=3.10,<4.0
Classifier: License :: OSI Approved :: MIT License
Classifier: Programming Language :: Python :: 3
Classifier: Programming Language :: Python :: 3.10
Classifier: Programming Language :: Python :: 3.11
Requires-Dist: beautifulsoup4 (>=4.12.2,<5.0.0)
Requires-Dist: pyzmq (>=25.1.1,<26.0.0)
Requires-Dist: tornado (>=6.4,<7.0)
